MANIFEST.in
README.txt
setup.cfg
setup.py
xhostplus/__init__.py
xhostplus.picturefolder.egg-info/PKG-INFO
xhostplus.picturefolder.egg-info/SOURCES.txt
xhostplus.picturefolder.egg-info/dependency_links.txt
xhostplus.picturefolder.egg-info/entry_points.txt
xhostplus.picturefolder.egg-info/namespace_packages.txt
xhostplus.picturefolder.egg-info/not-zip-safe
xhostplus.picturefolder.egg-info/paster_plugins.txt
xhostplus.picturefolder.egg-info/requires.txt
xhostplus.picturefolder.egg-info/top_level.txt
xhostplus/picturefolder/README.txt
xhostplus/picturefolder/__init__.py
xhostplus/picturefolder/config.py
xhostplus/picturefolder/configure.zcml
xhostplus/picturefolder/browser/__init__.py
xhostplus/picturefolder/browser/configure.zcml
xhostplus/picturefolder/browser/stylesheets/picturefolder.css
xhostplus/picturefolder/content/__init__.py
xhostplus/picturefolder/content/configure.zcml
xhostplus/picturefolder/content/picturefolder.py
xhostplus/picturefolder/interfaces/__init__.py
xhostplus/picturefolder/interfaces/picturefolder.py
xhostplus/picturefolder/locales/xhostplus.picturefolder.pot
xhostplus/picturefolder/locales/de/LC_MESSAGES/README.txt
xhostplus/picturefolder/locales/de/LC_MESSAGES/xhostplus.picturefolder.mo
xhostplus/picturefolder/locales/de/LC_MESSAGES/xhostplus.picturefolder.po
xhostplus/picturefolder/locales/en/LC_MESSAGES/README.txt
xhostplus/picturefolder/locales/en/LC_MESSAGES/xhostplus.picturefolder.mo
xhostplus/picturefolder/locales/en/LC_MESSAGES/xhostplus.picturefolder.po
xhostplus/picturefolder/portlets/__init__.py
xhostplus/picturefolder/portlets/configure.zcml
xhostplus/picturefolder/profiles/default/browserlayer.xml
xhostplus/picturefolder/profiles/default/cssregistry.xml
xhostplus/picturefolder/profiles/default/factorytool.xml
xhostplus/picturefolder/profiles/default/metadata.xml
xhostplus/picturefolder/profiles/default/portlets.xml
xhostplus/picturefolder/profiles/default/rolemap.xml
xhostplus/picturefolder/profiles/default/types.xml
xhostplus/picturefolder/profiles/default/types/Picture_Folder.xml
xhostplus/picturefolder/tests/__init__.py
xhostplus/picturefolder/tests/base.py
xhostplus/picturefolder/tests/test_doctest.py