Metadata-Version: 1.1
Name: xhostplus.picturefolder
Version: 1.0
Summary: Provides a folder with a optional image field
Home-page: http://www.xhostplus.at
Author: Andreas Stocker
Author-email: andreas.stocker@xhostplus.at
License: GPL
Keywords: Picture Image Folder Plugin Product Plone XHOSTPLUS
Platform: UNKNOWN
Classifier: Framework :: Plone
Classifier: Intended Audience :: Developers
Classifier: License :: OSI Approved :: GNU General Public License (GPL)
